MANIFEST.in
setup.py
Cubric.egg-info/PKG-INFO
Cubric.egg-info/SOURCES.txt
Cubric.egg-info/dependency_links.txt
Cubric.egg-info/not-zip-safe
Cubric.egg-info/requires.txt
Cubric.egg-info/top_level.txt
cubric/__init__.py
cubric/core.py
cubric/tasks.py
cubric/utils.py
cubric/contrib/__init__.py
cubric/contrib/servers/__init__.py
cubric/contrib/servers/ubuntu/__init__.py
cubric/contrib/servers/ubuntu/default/__init__.py
cubric/contrib/servers/ubuntu/default/templates/bash_profile.tmpl
cubric/contrib/servers/ubuntu/default/templates/bashrc.tmpl
cubric/contrib/servers/ubuntu/default/templates/nginx.conf.tmpl
cubric/contrib/servers/ubuntu/default/templates/profile.tmpl
cubric/contrib/servers/ubuntu/default/templates/supervisor.tmpl
cubric/contrib/servers/ubuntu/default/templates/supervisord.conf.tmpl
cubric/providers/__init__.py
cubric/providers/amazon.py
cubric/providers/rackspace.py